tests/__init__.py
tests/conftest.py
tests/test_ids.py
tests/test_memory.py
xerxes_protocol/__init__.py
xerxes_protocol/cli_util.py
xerxes_protocol/debug_serial.py
xerxes_protocol/defaults.py
xerxes_protocol/error_flags.py
xerxes_protocol/ids.py
xerxes_protocol/memory.py
xerxes_protocol/network.py
xerxes_protocol/hierarchy/__init__.py
xerxes_protocol/hierarchy/root.py
xerxes_protocol/hierarchy/leaves/__init__.py
xerxes_protocol/hierarchy/leaves/distance.py
xerxes_protocol/hierarchy/leaves/inclination.py
xerxes_protocol/hierarchy/leaves/leaf.py
xerxes_protocol/hierarchy/leaves/pressure.py
xerxes_protocol/hierarchy/leaves/strain.py
xerxes_protocol/hierarchy/leaves/utils.py
xerxes_protocol/units/__init__.py
xerxes_protocol/units/angle.py
xerxes_protocol/units/density.py
xerxes_protocol/units/length.py
xerxes_protocol/units/pressure.py
xerxes_protocol/units/temp.py
xerxes_protocol/units/unit.py
xerxes_protocol-1.4.5.dist-info/LICENSE
xerxes_protocol-1.4.5.dist-info/METADATA
xerxes_protocol-1.4.5.dist-info/WHEEL
xerxes_protocol-1.4.5.dist-info/entry_points.txt
xerxes_protocol-1.4.5.dist-info/top_level.txt
xerxes_protocol-1.4.5.dist-info/RECORD
