Metadata-Version: 2.1
Name: xerxes-protocol
Version: 1.4.5
Summary: Python implementation for xerxes-protocol
Home-page: https://github.com/metrotech-sk/xerxes-protocol
Author: Stanislav Rubint
Author-email: Stanislav Rubint <stanislav@rubint.sk>
License: MIT License
Project-URL: homepage, http://metrotech.sk
Project-URL: repository, https://github.com/metrotech-sk/xerxes-protocol
Keywords: xerxes
Requires-Python: >=3.8
License-File: LICENSE
Requires-Dist: pyserial
Requires-Dist: pytest
Requires-Dist: rich
Requires-Dist: coverage
